aima/__init__.py
aima/agents.py
aima/agents4e.py
aima/csp.py
aima/deep_learning4e.py
aima/doctests.py
aima/games.py
aima/games4e.py
aima/hobs/agents.py
aima/hobs/csp.py
aima/hobs/games.py
aima/hobs/learning.py
aima/hobs/logic.py
aima/hobs/mdp.py
aima/hobs/nlp.py
aima/hobs/planning.py
aima/hobs/probability.py
aima/hobs/search.py
aima/hobs/text.py
aima/hobs/utils.py
aima/images/IMAGE-CREDITS
aima/images/dirt.svg
aima/images/dirt05-icon.jpg
aima/images/makefile
aima/images/vacuum-icon.jpg
aima/images/vacuum.svg
aima/images/wall-icon.jpg
aima/ipyviews.py
aima/knowledge.py
aima/learning.py
aima/learning4e.py
aima/logic.py
aima/logic4e.py
aima/making_simple_decision4e.py
aima/mdp.py
aima/mdp4e.py
aima/nlp.py
aima/nlp4e.py
aima/notebook.py
aima/notebook4e.py
aima/perception4e.py
aima/planning.py
aima/probabilistic_learning.py
aima/probability.doctest
aima/probability.py
aima/probability4e.py
aima/reinforcement_learning.py
aima/reinforcement_learning4e.py
aima/rl.py
aima/search.py
aima/text.py
aima/utils.py
aima/utils4e.py
aima/utils4e_.py
aima/utils_.py
aima-2024.9.28.dist-info/LICENSE
aima-2024.9.28.dist-info/METADATA
aima-2024.9.28.dist-info/WHEEL
aima-2024.9.28.dist-info/entry_points.txt
aima-2024.9.28.dist-info/RECORD
