Metadata-Version: 2.1
Name: aima
Version: 2024.9.28
Summary: Artificial Intelligence a Modern Approach 4th Ed by Peter Norvig and Stuart Russel
Home-page: https://gitlab.com/tangibleai/community/aima
License: AGPL3
Keywords: AI,Artificial Intelligence,Artificial Intelligence a Modern Approach,NLP,Natural Language Processing,Virtual Assistant,chatbot,agent,Text Processing,Machine Learning,Graph Search,Search,AGI,AIMA
Author: Peter Norvig (norvig)
Author-email: peter.norvig@gmail.com
Requires-Python: >=3.7,<3.11
Classifier: Development Status :: 5 - Production/Stable
Classifier: Intended Audience :: Developers
Classifier: License :: OSI Approved :: GNU Affero General Public License v3
Classifier: License :: Other/Proprietary License
Classifier: Operating System :: OS Independent
Classifier: Programming Language :: Python :: 3
Classifier: Programming Language :: Python :: 3.7
Classifier: Programming Language :: Python :: 3.8
Classifier: Programming Language :: Python :: 3.9
Classifier: Programming Language :: Python :: 3.10
Classifier: Topic :: Software Development :: Libraries :: Python Modules
Classifier: Topic :: Text Processing :: Linguistic
Requires-Dist: cvxopt
Requires-Dist: image
Requires-Dist: ipython
Requires-Dist: ipythonblocks
Requires-Dist: ipywidgets
Requires-Dist: keras
Requires-Dist: matplotlib
Requires-Dist: networkx
Requires-Dist: numpy
Requires-Dist: opencv-python
Requires-Dist: pandas
Requires-Dist: pillow
Requires-Dist: pytest-cov
Requires-Dist: qpsolvers
Requires-Dist: scipy
Requires-Dist: sortedcontainers
Requires-Dist: tensorflow
Project-URL: Documentation, https://gitlab.com/tangibleai/community/aima
Project-URL: Repository, https://gitlab.com/tangibleai/community/aima
